freeplay_sdk/__init__.py
freeplay_sdk/api_support.py
freeplay_sdk/freeplay.py
freeplay_sdk-0.1.10.dist-info/METADATA
freeplay_sdk-0.1.10.dist-info/WHEEL
freeplay_sdk-0.1.10.dist-info/RECORD
