Metadata-Version: 2.1
Name: freeplay-sdk
Version: 0.1.10
Summary: 
License: MIT
Author: 228 Labs Engineering
Author-email: engineering@228labs.com
Requires-Python: >=3.7,<4
Classifier: License :: OSI Approved :: MIT License
Classifier: Programming Language :: Python :: 3
Classifier: Programming Language :: Python :: 3.7
Classifier: Programming Language :: Python :: 3.8
Classifier: Programming Language :: Python :: 3.9
Classifier: Programming Language :: Python :: 3.10
Classifier: Programming Language :: Python :: 3.11
Requires-Dist: dacite (>=1.8.0,<2.0.0)
Requires-Dist: requests (>=2.20.0,<3.0.0dev)
